immichporter/__init__.py
immichporter/cli.py
immichporter/commands.py
immichporter/database.py
immichporter/models.py
immichporter/schemas.py
immichporter/db/__init__.py
immichporter/db/commands.py
immichporter/gphotos/__init__.py
immichporter/gphotos/commands.py
immichporter/gphotos/scraper.py
immichporter/gphotos/settings.py
immichporter/gphotos/utils.py
immichporter/immich/__init__.py
immichporter/immich/commands.py
immichporter/immich/immich.py
immichporter/immich/models.py
immichporter/immich/client/__init__.py
immichporter/immich/client/client.py
immichporter/immich/client/errors.py
immichporter/immich/client/types.py
immichporter/immich/client/api/__init__.py
immichporter/immich/client/api/activities/__init__.py
immichporter/immich/client/api/activities/create_activity.py
immichporter/immich/client/api/activities/delete_activity.py
immichporter/immich/client/api/activities/get_activities.py
immichporter/immich/client/api/activities/get_activity_statistics.py
immichporter/immich/client/api/albums/__init__.py
immichporter/immich/client/api/albums/add_assets_to_album.py
immichporter/immich/client/api/albums/add_assets_to_albums.py
immichporter/immich/client/api/albums/add_users_to_album.py
immichporter/immich/client/api/albums/create_album.py
immichporter/immich/client/api/albums/delete_album.py
immichporter/immich/client/api/albums/get_album_info.py
immichporter/immich/client/api/albums/get_album_statistics.py
immichporter/immich/client/api/albums/get_all_albums.py
immichporter/immich/client/api/albums/remove_asset_from_album.py
immichporter/immich/client/api/albums/remove_user_from_album.py
immichporter/immich/client/api/albums/update_album_info.py
immichporter/immich/client/api/albums/update_album_user.py
immichporter/immich/client/api/api_keys/__init__.py
immichporter/immich/client/api/api_keys/create_api_key.py
immichporter/immich/client/api/api_keys/delete_api_key.py
immichporter/immich/client/api/api_keys/get_api_key.py
immichporter-0.0.5.dist-info/METADATA
immichporter-0.0.5.dist-info/WHEEL
immichporter-0.0.5.dist-info/entry_points.txt
immichporter-0.0.5.dist-info/licenses/LICENSE
immichporter-0.0.5.dist-info/RECORD
