Metadata-Version: 2.4
Name: immichporter
Version: 0.0.5
Summary: Import photos from various sources to Immich
Project-URL: Repository, https://github.com/burgdev/immichporter
Project-URL: Documentation, https://burgdev.github.io/immichporter/
Project-URL: Changelog, https://github.com/burgdev/immichporter/blob/main/CHANGELOG.md
Project-URL: Releases, https://github.com/burgdev/immichporter/releases
License: MIT
License-File: LICENSE
Classifier: Development Status :: 4 - Beta
Classifier: Intended Audience :: Developers
Classifier: License :: OSI Approved :: MIT License
Classifier: Programming Language :: Python :: 3.11
Classifier: Programming Language :: Python :: 3.12
Classifier: Topic :: Multimedia :: Graphics :: Graphics Conversion
Classifier: Topic :: Software Development :: Libraries :: Python Modules
Requires-Python: >=3.11
Requires-Dist: attrs>=25.3.0
Requires-Dist: click
Requires-Dist: httpx>=0.28.1
Requires-Dist: loguru
Requires-Dist: platformdirs>=4.4.0
Requires-Dist: playwright
Requires-Dist: prompt-toolkit>=3.0.52
Requires-Dist: psycopg2-binary>=2.9.11
Requires-Dist: pydantic>=2.11.10
Requires-Dist: python-dateutil
Requires-Dist: rich
Requires-Dist: sqlalchemy
